LICENSE.md
MANIFEST.in
README.rst
pyproject.toml
requirements.core.txt
requirements.txt
setup.py
core_main_registry_app/__init__.py
core_main_registry_app/admin.py
core_main_registry_app/apps.py
core_main_registry_app/constants.py
core_main_registry_app/discover.py
core_main_registry_app/menus.py
core_main_registry_app/models.py
core_main_registry_app/settings.py
core_main_registry_app/tasks.py
core_main_registry_app/urls.py
core_main_registry_app.egg-info/PKG-INFO
core_main_registry_app.egg-info/SOURCES.txt
core_main_registry_app.egg-info/dependency_links.txt
core_main_registry_app.egg-info/requires.txt
core_main_registry_app.egg-info/top_level.txt
core_main_registry_app/commons/__init__.py
core_main_registry_app/commons/constants.py
core_main_registry_app/components/__init__.py
core_main_registry_app/components/category/__init__.py
core_main_registry_app/components/category/api.py
core_main_registry_app/components/category/models.py
core_main_registry_app/components/custom_resource/__init__.py
core_main_registry_app/components/custom_resource/admin_site.py
core_main_registry_app/components/custom_resource/api.py
core_main_registry_app/components/custom_resource/models.py
core_main_registry_app/components/data/__init__.py
core_main_registry_app/components/data/access_control.py
core_main_registry_app/components/data/api.py
core_main_registry_app/components/refinement/__init__.py
core_main_registry_app/components/refinement/api.py
core_main_registry_app/components/refinement/models.py
core_main_registry_app/components/template/__init__.py
core_main_registry_app/components/template/api.py
core_main_registry_app/components/version_manager/__init__.py
core_main_registry_app/components/version_manager/api.py
core_main_registry_app/migrations/0001_initial.py
core_main_registry_app/migrations/0002_init_data.py
core_main_registry_app/migrations/__init__.py
core_main_registry_app/rest/__init__.py
core_main_registry_app/rest/urls.py
core_main_registry_app/rest/data/__init__.py
core_main_registry_app/rest/data/views.py
core_main_registry_app/rest/template_version_manager/__init__.py
core_main_registry_app/rest/template_version_manager/views.py
core_main_registry_app/rest/workspace/__init__.py
