Metadata-Version: 2.1
Name: core-main-registry-app
Version: 2.19.0
Summary: Main functionalities for the registry project
Home-page: https://github.com/usnistgov/core_main_registry_app
Author: NIST IT Lab
Author-email: itl_inquiries@nist.gov
License-File: LICENSE.md
